query_handler/__init__.py
query_handler/query_dto.py
ecomm_base-1.1.4.dist-info/METADATA
ecomm_base-1.1.4.dist-info/WHEEL
ecomm_base-1.1.4.dist-info/top_level.txt
ecomm_base-1.1.4.dist-info/RECORD
