Metadata-Version: 2.2
Name: ecomm_base
Version: 1.1.4
Summary: This package contains base code for all services e.g. Query DTO and Model Enums
Author: Novacept
Author-email: mahesh.chavan@novacept.io
Classifier: Programming Language :: Python :: 3
Classifier: License :: OSI Approved :: MIT License
Classifier: Operating System :: OS Independent
Dynamic: author
Dynamic: author-email
Dynamic: classifier
Dynamic: description
Dynamic: description-content-type
Dynamic: summary
